jupyterlab_horizon_theme/__init__.py
jupyterlab_horizon_theme/_version.py
jupyterlab_horizon_theme-4.0.2.data/data/share/jupyter/labextensions/@mohirio/jupyterlab-horizon-theme/package.json
jupyterlab_horizon_theme-4.0.2.data/data/share/jupyter/labextensions/@mohirio/jupyterlab-horizon-theme/static/568.58bf7d4f667802796309.js
jupyterlab_horizon_theme-4.0.2.data/data/share/jupyter/labextensions/@mohirio/jupyterlab-horizon-theme/static/remoteEntry.0129ee2901d8716e910c.js
jupyterlab_horizon_theme-4.0.2.data/data/share/jupyter/labextensions/@mohirio/jupyterlab-horizon-theme/static/style.js
jupyterlab_horizon_theme-4.0.2.data/data/share/jupyter/labextensions/@mohirio/jupyterlab-horizon-theme/static/third-party-licenses.json
jupyterlab_horizon_theme-4.0.2.data/data/share/jupyter/labextensions/@mohirio/jupyterlab-horizon-theme/themes/@mohirio/jupyterlab-horizon-theme/2967dd73df838d2a2d39.ttf
jupyterlab_horizon_theme-4.0.2.data/data/share/jupyter/labextensions/@mohirio/jupyterlab-horizon-theme/themes/@mohirio/jupyterlab-horizon-theme/80922933add5aaad3870.ttf
jupyterlab_horizon_theme-4.0.2.data/data/share/jupyter/labextensions/@mohirio/jupyterlab-horizon-theme/themes/@mohirio/jupyterlab-horizon-theme/index.css
jupyterlab_horizon_theme-4.0.2.data/data/share/jupyter/labextensions/@mohirio/jupyterlab-horizon-theme/themes/@mohirio/jupyterlab-horizon-theme/index.js
jupyterlab_horizon_theme-4.0.2.data/data/share/jupyter/labextensions/@mohirio/jupyterlab-horizon-theme/install.json
jupyterlab_horizon_theme-4.0.2.dist-info/METADATA
jupyterlab_horizon_theme-4.0.2.dist-info/WHEEL
jupyterlab_horizon_theme-4.0.2.dist-info/licenses/LICENSE
jupyterlab_horizon_theme-4.0.2.dist-info/RECORD
