Metadata-Version: 2.1
Name: jupyterlab_horizon_theme
Version: 4.0.2
Summary: VSCode Horizon Theme port for JupyterLab
Project-URL: Homepage, https://github.com/mohirio/jupyterlab-horizon-theme
Project-URL: Bug Tracker, https://github.com/mohirio/jupyterlab-horizon-theme/issues
Project-URL: Repository, https://github.com/mohirio/jupyterlab-horizon-theme.git
Author-email: Mohammad Almogbel <almogbelmohi@gmail.com>
License: Copyright (c) 2019, Mohammad Almogbel
License-File: LICENSE
Classifier: Framework :: Jupyter
Classifier: Framework :: Jupyter :: JupyterLab
Classifier: Framework :: Jupyter :: JupyterLab :: 4
Classifier: Framework :: Jupyter :: JupyterLab :: Extensions
Classifier: Framework :: Jupyter :: JupyterLab :: Extensions :: Prebuilt
Classifier: License :: OSI Approved :: BSD License
Classifier: Programming Language :: Python
Classifier: Programming Language :: Python :: 3
Classifier: Programming Language :: Python :: 3.8
Classifier: Programming Language :: Python :: 3.9
Classifier: Programming Language :: Python :: 3.10
Classifier: Programming Language :: Python :: 3.11
Classifier: Programming Language :: Python :: 3.12
Requires-Python: >=3.8
